pycategory/__init__.py
pycategory/applicative.py
pycategory/collection.py
pycategory/constraints.py
pycategory/either.py
pycategory/extension.py
pycategory/extractor.py
pycategory/function_.py
pycategory/functor.py
pycategory/monad.py
pycategory/option.py
pycategory/pipeline.py
pycategory/processor.py
pycategory/py.typed
pycategory/try_.py
pycategory-0.1.2.dist-info/LICENSE
pycategory-0.1.2.dist-info/METADATA
pycategory-0.1.2.dist-info/WHEEL
pycategory-0.1.2.dist-info/RECORD
