Metadata-Version: 2.1
Name: pycategory
Version: 0.1.2
Summary: Python implementation of the Scala standard library.
Home-page: https://github.com/usabarashi/pycategory
License: MIT
Keywords: Functional,Scala
Author: usabarashi
Requires-Python: >=3.10,<4.0
Classifier: License :: OSI Approved :: MIT License
Classifier: Programming Language :: Python :: 3
Classifier: Programming Language :: Python :: 3.10
Classifier: Programming Language :: Python :: 3.11
Classifier: Programming Language :: Python :: 3.12
Project-URL: Repository, https://github.com/usabarashi/pycategory
